lmdlang/expression/__init__.py
lmdlang/expression/basic.py
lmdlang/expression/definitions.py
lmdlang/expression/interface.py
lmdlang/language.py
lmdlang/main.py
lmdlang/runtime/__init__.py
lmdlang/runtime/terms.py
lmdlang/runtime/variable_names_manager.py
lmdlang/syntax/__init__.py
lmdlang/syntax/classic_expression.py
lmdlang/syntax/classic_program.py
lmdlang/syntax/tactics_core.py
lmdlang-0.1.0.dist-info/LICENSE
lmdlang-0.1.0.dist-info/METADATA
lmdlang-0.1.0.dist-info/WHEEL
lmdlang-0.1.0.dist-info/entry_points.txt
lmdlang-0.1.0.dist-info/RECORD
